authera/apps.py
authera/baseUser.py
authera/scenario.py
authera/tokens.py
authera/urls.py
authera/utils.py
authera/views.py
authera-1.1.2.dist-info/licenses/LICENSE
authera-1.1.2.dist-info/METADATA
authera-1.1.2.dist-info/WHEEL
authera-1.1.2.dist-info/top_level.txt
authera-1.1.2.dist-info/RECORD
