Metadata-Version: 2.4
Name: authera
Version: 1.1.2
Summary: A modern authentication and user management package for Django (Clerk-style)
Home-page: https://github.com/algonouire/authera
Author: AlgoNouir
Author-email: Algonouir <algo.mahdi.nouri@gmail.com>
License: MIT
Project-URL: Homepage, https://github.com/algonouire/authera
Project-URL: Issues, https://github.com/algonouire/authera/issues
Keywords: django,authentication,clerk,jwt,rest,user-management
Requires-Python: >=3.9
License-File: LICENSE
Requires-Dist: Django>=4.2
Requires-Dist: djangorestframework>=3.15
Requires-Dist: djangorestframework-simplejwt>=5.3.0
Dynamic: author
Dynamic: home-page
Dynamic: license-file
Dynamic: requires-python
